surquest/fastapi/schemas/args.py
surquest/fastapi/schemas/responses/__init__.py
surquest/fastapi/schemas/responses/base.py
surquest/fastapi/schemas/responses/info.py
surquest/fastapi/schemas/responses/message.py
surquest/fastapi/schemas/responses/metadata.py
surquest/fastapi/schemas/responses/responses.py
surquest/fastapi/schemas/responses/status.py
surquest_fastapi_schemas-0.0.1rc10.dist-info/METADATA
surquest_fastapi_schemas-0.0.1rc10.dist-info/WHEEL
surquest_fastapi_schemas-0.0.1rc10.dist-info/licenses/LICENSE
surquest_fastapi_schemas-0.0.1rc10.dist-info/RECORD
