Metadata-Version: 2.1
Name: surquest-fastapi-schemas
Version: 0.0.1rc10
Summary: This project provides collection of standard schemas for FastAPI framework as: startDate, endDate, offset, limit, etc.
Project-URL: Homepage, https://github.com/surquest/python-fastapi-schemas
Project-URL: Bug Tracker, https://github.com/surquest/python-fastapi-schemas/issues
Author-email: Michal Švarc <michal.svarc@surquest.com>
License-File: LICENSE
Requires-Dist: fastapi>=0.91.0
Provides-Extra: test
Requires-Dist: pytest-cov>=4.0.0; extra == 'test'
Requires-Dist: pytest>=7.2.1; extra == 'test'
